MANIFEST.in
README.md
TODO.md
pip-reinstall.sh
requirements.txt
setup.py
workspacemanager/__init__.py
workspacemanager/condaadd.py
workspacemanager/condainst.py
workspacemanager/dist.py
workspacemanager/help.py
workspacemanager/pewadd.py
workspacemanager/pewinst.py
workspacemanager/setup.py
workspacemanager/utils.py
workspacemanager.egg-info/PKG-INFO
workspacemanager.egg-info/SOURCES.txt
workspacemanager.egg-info/dependency_links.txt
workspacemanager.egg-info/entry_points.txt
workspacemanager.egg-info/requires.txt
workspacemanager.egg-info/top_level.txt
workspacemanager/__pycache__/__init__.cpython-35.pyc
workspacemanager/__pycache__/__init__.cpython-36.pyc
workspacemanager/__pycache__/condaadd.cpython-36.pyc
workspacemanager/__pycache__/deps.cpython-35.pyc
workspacemanager/__pycache__/deps.cpython-36.pyc
workspacemanager/__pycache__/dist.cpython-35.pyc
workspacemanager/__pycache__/dist.cpython-36.pyc
workspacemanager/__pycache__/freeze.cpython-35.pyc
workspacemanager/__pycache__/freeze.cpython-36.pyc
workspacemanager/__pycache__/help.cpython-35.pyc
workspacemanager/__pycache__/help.cpython-36.pyc
workspacemanager/__pycache__/path.cpython-35.pyc
workspacemanager/__pycache__/path.cpython-36.pyc
workspacemanager/__pycache__/req.cpython-35.pyc
workspacemanager/__pycache__/req.cpython-36.pyc
workspacemanager/__pycache__/setup.cpython-35.pyc
workspacemanager/__pycache__/setup.cpython-36.pyc
workspacemanager/__pycache__/utils.cpython-35.pyc
workspacemanager/__pycache__/utils.cpython-36.pyc
workspacemanager/__pycache__/venv.cpython-35.pyc
workspacemanager/__pycache__/venv.cpython-36.pyc
workspacemanager/__pycache__/workon.cpython-35.pyc
workspacemanager/__pycache__/workon.cpython-36.pyc
workspacemanager/_trash/deps.py
workspacemanager/_trash/freeze.py
workspacemanager/_trash/pew-install-current-req.py
workspacemanager/_trash/venv.py
workspacemanager/_trash/workon.py
workspacemanager/dist-templates/rsync-all.sh
workspacemanager/setup-templates/.gitignore
workspacemanager/setup-templates/LICENCE.txt
workspacemanager/setup-templates/MANIFEST.in
workspacemanager/setup-templates/README.md
workspacemanager/setup-templates/local-dependencies.txt
workspacemanager/setup-templates/setup.py
workspacemanager/src/pyuserinput/PyUserInput.egg-info/PKG-INFO
workspacemanager/src/pyuserinput/PyUserInput.egg-info/SOURCES.txt
workspacemanager/src/pyuserinput/PyUserInput.egg-info/dependency_links.txt
workspacemanager/src/pyuserinput/PyUserInput.egg-info/requires.txt
workspacemanager/src/pyuserinput/PyUserInput.egg-info/top_level.txt
