Metadata-Version: 1.1
Name: workspacemanager
Version: 0.3.2
Summary: This tool can manage a workspace by providing some useful functions (generation of the setup file and others, generate a virtual env according to the project name, install your own dependencies, generate dist of all dependencies...). See the readme for more informations.
Home-page: UNKNOWN
Author: hayj
Author-email: hj@hayj.fr
License: UNKNOWN
Platform: UNKNOWN
Classifier: Programming Language :: Python
Classifier: Development Status :: 1 - Planning
Classifier: License :: OSI Approved :: MIT License
Classifier: Natural Language :: English
Classifier: Operating System :: OS Independent
Classifier: Programming Language :: Python :: 2.7
Classifier: Topic :: Utilities
